setup.py
Cserial_test/__init__.py
Cserial_test.egg-info/PKG-INFO
Cserial_test.egg-info/SOURCES.txt
Cserial_test.egg-info/dependency_links.txt
Cserial_test.egg-info/not-zip-safe
Cserial_test.egg-info/requires.txt
Cserial_test.egg-info/top_level.txt