Metadata-Version: 1.0
Name: Cserial-test
Version: 0.1
Summary: test package for CSDT serial communication
Home-page: UNKNOWN
Author: Ethan Riley
Author-email: rileye4@rpi.edu
License: MIT
Platform: UNKNOWN
